UE_OLED/__init__.py
UE_OLED/ssd1306.py
UE_OLED-0.2.dist-info/LICENSE
UE_OLED-0.2.dist-info/METADATA
UE_OLED-0.2.dist-info/WHEEL
UE_OLED-0.2.dist-info/top_level.txt
UE_OLED-0.2.dist-info/RECORD
